[
	[
		{
			"leftPath":"src/java/fr/jayasoft/ivy/resolver/BasicResolver.java",
			"leftBegin":700,
			"leftEnd":700,
			"rightPath":"src/java/fr/jayasoft/ivy/resolver/BasicResolver.java",
			"rightBegin":694,
			"rightEnd":694
		}
	],
	[
		{
			"leftPath":"src/java/fr/jayasoft/ivy/Ivy.java",
			"leftBegin":2336,
			"leftEnd":2335,
			"rightPath":"src/java/fr/jayasoft/ivy/Ivy.java",
			"rightBegin":2338,
			"rightEnd":2340
		}
	],
	[
		{
			"leftPath":"src/java/fr/jayasoft/ivy/Ivy.java",
			"leftBegin":1815,
			"leftEnd":1817,
			"rightPath":"src/java/fr/jayasoft/ivy/Ivy.java",
			"rightBegin":1821,
			"rightEnd":1821
		},
		{
			"leftPath":"src/java/fr/jayasoft/ivy/Ivy.java",
			"leftBegin":1294,
			"leftEnd":1296,
			"rightPath":"src/java/fr/jayasoft/ivy/Ivy.java",
			"rightBegin":1302,
			"rightEnd":1302
		},
		{
			"leftPath":"src/java/fr/jayasoft/ivy/repository/vsftp/VsftpRepository.java",
			"leftBegin":219,
			"leftEnd":221,
			"rightPath":"src/java/fr/jayasoft/ivy/repository/vsftp/VsftpRepository.java",
			"rightBegin":219,
			"rightEnd":219
		},
		{
			"leftPath":"src/java/fr/jayasoft/ivy/Ivy.java",
			"leftBegin":1125,
			"leftEnd":1124,
			"rightPath":"src/java/fr/jayasoft/ivy/Ivy.java",
			"rightBegin":1123,
			"rightEnd":1132
		},
		{
			"leftPath":"src/java/fr/jayasoft/ivy/Ivy.java",
			"leftBegin":1089,
			"leftEnd":1091,
			"rightPath":"src/java/fr/jayasoft/ivy/Ivy.java",
			"rightBegin":1089,
			"rightEnd":1089
		},
		{
			"leftPath":"src/java/fr/jayasoft/ivy/Ivy.java",
			"leftBegin":2203,
			"leftEnd":2205,
			"rightPath":"src/java/fr/jayasoft/ivy/Ivy.java",
			"rightBegin":2207,
			"rightEnd":2207
		}
	],
	[
		{
			"leftPath":"src/java/fr/jayasoft/ivy/resolver/BasicResolver.java",
			"leftBegin":691,
			"leftEnd":693,
			"rightPath":"src/java/fr/jayasoft/ivy/resolver/BasicResolver.java",
			"rightBegin":687,
			"rightEnd":687
		},
		{
			"leftPath":"src/java/fr/jayasoft/ivy/resolver/BasicResolver.java",
			"leftBegin":168,
			"leftEnd":170,
			"rightPath":"src/java/fr/jayasoft/ivy/resolver/BasicResolver.java",
			"rightBegin":166,
			"rightEnd":166
		},
		{
			"leftPath":"src/java/fr/jayasoft/ivy/resolver/BasicResolver.java",
			"leftBegin":163,
			"leftEnd":165,
			"rightPath":"src/java/fr/jayasoft/ivy/resolver/BasicResolver.java",
			"rightBegin":163,
			"rightEnd":163
		}
	],
	[
		{
			"leftPath":"src/java/fr/jayasoft/ivy/resolver/ChainResolver.java",
			"leftBegin":80,
			"leftEnd":82,
			"rightPath":"src/java/fr/jayasoft/ivy/resolver/ChainResolver.java",
			"rightBegin":80,
			"rightEnd":80
		}
	],
	[
		{
			"leftPath":"src/java/fr/jayasoft/ivy/resolver/AbstractResolver.java",
			"leftBegin":93,
			"leftEnd":93,
			"rightPath":"src/java/fr/jayasoft/ivy/resolver/AbstractResolver.java",
			"rightBegin":93,
			"rightEnd":100
		}
	]
]